pygments_kibana/__init__.py
pygments_kibana/kibana_lexer.py
pygments_kibana-0.0.1.dist-info/LICENSE
pygments_kibana-0.0.1.dist-info/METADATA
pygments_kibana-0.0.1.dist-info/WHEEL
pygments_kibana-0.0.1.dist-info/entry_points.txt
pygments_kibana-0.0.1.dist-info/top_level.txt
pygments_kibana-0.0.1.dist-info/RECORD
