Metadata-Version: 2.1
Name: pygments-kibana
Version: 0.0.1
Summary: Pygments lexer for Kibana Console input
Home-page: UNKNOWN
Author: Honza Král
Author-email: honza.kral@gmail.com
License: UNKNOWN
Platform: UNKNOWN
Requires-Dist: Pygments
